tests/__init__.py
tests/test_components.py
tests/test_input.py
tests/test_options.py
tests/test_runner.py
tests/test_xml_functionality.py
xtp_job_control/__init__.py
xtp_job_control/results.py
xtp_job_control/runner.py
xtp_job_control/xml_editor.py
xtp_job_control/input/__init__.py
xtp_job_control/input/schemas.py
xtp_job_control/input/validate_input.py
xtp_job_control/workflows/__init__.py
xtp_job_control/workflows/dftgwbse.py
xtp_job_control/workflows/kmc.py
xtp_job_control/workflows/run_workflow.py
xtp_job_control/workflows/transport.py
xtp_job_control/workflows/workflow_components.py
xtp_job_control/workflows/xtp_workflow.py
xtp_job_control-0.1.1.data/scripts/run_xtp_workflow.py
xtp_job_control-0.1.1.dist-info/LICENSE
xtp_job_control-0.1.1.dist-info/METADATA
xtp_job_control-0.1.1.dist-info/WHEEL
xtp_job_control-0.1.1.dist-info/top_level.txt
xtp_job_control-0.1.1.dist-info/RECORD
