Metadata-Version: 2.1
Name: xtp-job-control
Version: 0.1.1
Summary: Workflow engine to use the VOTCA-XTP library
Home-page: https://github.com/votca/xtp_job_control
Author: ['Felipe Zapata']
Author-email: fzapata@esciencecenter.nl
License: Apache-2.0
Keywords: chemistry materials
Platform: UNKNOWN
Classifier: License :: OSI Approved :: Apache Software License
Classifier: Intended Audience :: Science/Research
Classifier: Programming Language :: Python :: 3.6
Classifier: Development Status :: 4 - Beta
Classifier: Topic :: Scientific/Engineering :: Chemistry
Requires-Dist: noodles[numpy]
Requires-Dist: pyyaml
Requires-Dist: schema
Provides-Extra: test
Requires-Dist: pytest (>=4.1.0) ; extra == 'test'
Requires-Dist: pytest-cov (>=2.6.1) ; extra == 'test'
Requires-Dist: coverage ; extra == 'test'
Requires-Dist: codacy-coverage ; extra == 'test'
